galgenmaennchen/__init__.py
galgenmaennchen/_galgenmaennchen.py
galgenmaennchen/galgenmaennchen.py
galgenmaennchen-0.3.0.dist-info/LICENSE
galgenmaennchen-0.3.0.dist-info/METADATA
galgenmaennchen-0.3.0.dist-info/WHEEL
galgenmaennchen-0.3.0.dist-info/top_level.txt
galgenmaennchen-0.3.0.dist-info/RECORD
